swarmauri_toolkit_jupytertoolkit/JupyterToolkit.py
swarmauri_toolkit_jupytertoolkit/__init__.py
swarmauri_toolkit_jupytertoolkit-0.2.5.dist-info/LICENSE
swarmauri_toolkit_jupytertoolkit-0.2.5.dist-info/METADATA
swarmauri_toolkit_jupytertoolkit-0.2.5.dist-info/WHEEL
swarmauri_toolkit_jupytertoolkit-0.2.5.dist-info/entry_points.txt
swarmauri_toolkit_jupytertoolkit-0.2.5.dist-info/RECORD
