Metadata-Version: 2.3
Name: swarmauri_toolkit_jupytertoolkit
Version: 0.2.5
Summary: A unified toolkit for aggregating standalone jupyter notebook tools.
License: Apache-2.0
Author: Jacob Stewart
Author-email: jacob@swarmauri.com
Requires-Python: >=3.10,<3.13
Classifier: License :: OSI Approved :: Apache Software License
Classifier: Programming Language :: Python :: 3.10
Classifier: Programming Language :: Python :: 3.11
Classifier: Programming Language :: Python :: 3.12
Classifier: Programming Language :: Python :: 3.13
Requires-Dist: pydantic
Requires-Dist: swarmauri_base
Requires-Dist: swarmauri_core
Requires-Dist: swarmauri_standard
Requires-Dist: swarmauri_tool_jupyterclearoutput
Requires-Dist: swarmauri_tool_jupyterdisplay
Requires-Dist: swarmauri_tool_jupyterdisplayhtml
Requires-Dist: swarmauri_tool_jupyterexecuteandconvert
Requires-Dist: swarmauri_tool_jupyterexecutecell
Requires-Dist: swarmauri_tool_jupyterexecutenotebook
Requires-Dist: swarmauri_tool_jupyterexecutenotebookwithparameters
Requires-Dist: swarmauri_tool_jupyterexporthtml
Requires-Dist: swarmauri_tool_jupyterexportlatex
Requires-Dist: swarmauri_tool_jupyterexportmarkdown
Requires-Dist: swarmauri_tool_jupyterexportpython
Requires-Dist: swarmauri_tool_jupyterfromdict
Requires-Dist: swarmauri_tool_jupytergetiopubmessage
Requires-Dist: swarmauri_tool_jupytergetshellmessage
Requires-Dist: swarmauri_tool_jupyterreadnotebook
Requires-Dist: swarmauri_tool_jupyterruncell
Requires-Dist: swarmauri_tool_jupytershutdownkernel
Requires-Dist: swarmauri_tool_jupyterstartkernel
Requires-Dist: swarmauri_tool_jupytervalidatenotebook
Requires-Dist: swarmauri_tool_jupyterwritenotebook
